LICENSE
README.md
setup.py
src/qrgrader/__init__.py
src/qrgrader/buttons.py
src/qrgrader/buttons2.py
src/qrgrader/code.py
src/qrgrader/code_set.py
src/qrgrader/common.py
src/qrgrader/dialogs.py
src/qrgrader/encrypt.py
src/qrgrader/gdrive.py
src/qrgrader/generator.py
src/qrgrader/page_processor.py
src/qrgrader/pdf_tree.py
src/qrgrader/qrgenerator.py
src/qrgrader/qrgui.py
src/qrgrader/qrscanner.py
src/qrgrader/qrsheets.py
src/qrgrader/qrtable.py
src/qrgrader/qrworkspace.py
src/qrgrader/rubric.py
src/qrgrader/secret.py
src/qrgrader/utils.py
src/qrgrader/widget_utils.py
src/qrgrader.egg-info/PKG-INFO
src/qrgrader.egg-info/SOURCES.txt
src/qrgrader.egg-info/dependency_links.txt
src/qrgrader.egg-info/entry_points.txt
src/qrgrader.egg-info/requires.txt
src/qrgrader.egg-info/top_level.txt
src/qrgrader/latex/main.tex
src/qrgrader/latex/qrgrader.sty