Metadata-Version: 2.4
Name: qrgrader
Version: 0.0.19
Summary: A framework for automatic grading of exams using QR codes
Home-page: https://github.com/dantard/qrgrader
Author: Danilo Tardioli
Author-email: dantard@unizar.es
Classifier: Programming Language :: Python :: 3
Classifier: Operating System :: OS Independent
Requires-Python: >=3.10
License-File: LICENSE
Requires-Dist: pyqt5
Requires-Dist: pymupdf>=1.18.17
Requires-Dist: easyconfig2
Requires-Dist: zxing-cpp
Requires-Dist: gspread
Requires-Dist: pydrive2
Requires-Dist: opencv-python-headless
Requires-Dist: pandas
Requires-Dist: swikv4-minimal
Dynamic: author
Dynamic: author-email
Dynamic: classifier
Dynamic: description
Dynamic: description-content-type
Dynamic: home-page
Dynamic: license-file
Dynamic: requires-dist
Dynamic: requires-python
Dynamic: summary
